pytest_dummynet/__init__.py
pytest_dummynet/docker_shell.py
pytest_dummynet/dummy_net.py
pytest_dummynet/dummy_net_factory.py
pytest_dummynet/fixtures.py
pytest_dummynet/host_shell.py
pytest_dummynet/namespace_shell.py
pytest_dummynet-2.1.0.dist-info/LICENSE.rst
pytest_dummynet-2.1.0.dist-info/METADATA
pytest_dummynet-2.1.0.dist-info/WHEEL
pytest_dummynet-2.1.0.dist-info/entry_points.txt
pytest_dummynet-2.1.0.dist-info/top_level.txt
pytest_dummynet-2.1.0.dist-info/RECORD
